flavorpy/__init__.py
flavorpy/constructterms/__init__.py
flavorpy/constructterms/calculations.py
flavorpy/constructterms/field.py
flavorpy/constructterms/group.py
flavorpy/constructterms/groups/groups.py
flavorpy/docs/Makefile
flavorpy/docs/conf.py
flavorpy/docs/constructterms.rst
flavorpy/docs/index.rst
flavorpy/docs/make.bat
flavorpy/docs/modelfitting.rst
flavorpy/docs/_build/doctrees/constructterms.doctree
flavorpy/docs/_build/doctrees/environment.pickle
flavorpy/docs/_build/doctrees/index.doctree
flavorpy/docs/_build/doctrees/modelfitting.doctree
flavorpy/docs/_build/doctrees/examples/arxiv2006dot03058.doctree
flavorpy/docs/_build/doctrees/examples/detailedexample_constructterms.doctree
flavorpy/docs/_build/doctrees/examples/detailedexample_modelfitting.doctree
flavorpy/docs/_build/doctrees/examples/detailedexample_modelfitting_old.doctree
flavorpy/docs/_build/doctrees/examples/examples_page.doctree
flavorpy/docs/_build/doctrees/examples/simpleexample_constructterms.doctree
flavorpy/docs/_build/doctrees/examples/simpleexample_modelfitting.doctree
flavorpy/docs/_build/doctrees/examples/simpleexample_modelfitting_old.doctree
flavorpy/docs/_build/html/.buildinfo
flavorpy/docs/_build/html/constructterms.html
flavorpy/docs/_build/html/genindex.html
flavorpy/docs/_build/html/index.html
flavorpy/docs/_build/html/modelfitting.html
flavorpy/docs/_build/html/objects.inv
flavorpy/docs/_build/html/py-modindex.html
flavorpy/docs/_build/html/search.html
flavorpy/docs/_build/html/searchindex.js
flavorpy/docs/_build/html/_images/arxiv2006dot03058_IO_Retau_dpi.png
flavorpy/docs/_build/html/_images/arxiv2006dot03058_IO_modulispace.png
flavorpy/docs/_build/html/_images/arxiv2006dot03058_IO_s23_dpi.png
flavorpy/docs/_build/html/_images/arxiv2006dot03058_NO_Retau_dpi.png
flavorpy/docs/_build/html/_images/arxiv2006dot03058_NO_modulispace.png
flavorpy/docs/_build/html/_images/arxiv2006dot03058_NO_s23_dpi.png
flavorpy-0.2.0.dist-info/METADATA
flavorpy-0.2.0.dist-info/WHEEL
flavorpy-0.2.0.dist-info/licenses/LICENSE
flavorpy-0.2.0.dist-info/RECORD
