Metadata-Version: 2.3
Name: flavorpy
Version: 0.2.0
Summary: Library for calculations around discrete flavor symmetries in particle physics
Project-URL: Homepage, https://flavorpy.github.io/FlavorPy
Project-URL: Repository, https://github.com/FlavorPy/FlavorPy
Author-email: Alexander Baur <alexander.baur@tum.de>
License: BSD 3-Clause License
License-File: LICENSE
Keywords: discrete symmetry,flavor model,flavor symmetry,modular flavor symmetry,particle physics,standard model
Classifier: Intended Audience :: Science/Research
Classifier: License :: OSI Approved :: BSD License
Classifier: Operating System :: OS Independent
Classifier: Programming Language :: Python :: 3
Classifier: Topic :: Scientific/Engineering :: Physics
Requires-Python: >=3.8
Requires-Dist: emcee>=3.0.0
Requires-Dist: lmfit>=1.0.3
Requires-Dist: matplotlib>=3.4.3
Requires-Dist: numpy>=1.23.4
Requires-Dist: pandas>=1.5.1
Requires-Dist: scipy>=1.9.3
